conf/__init__.py
conf/base.py
mlops_pipeline_feature_v1/__init__.py
mlops_pipeline_feature_v1/extract.py
mlops_pipeline_feature_v1/load.py
mlops_pipeline_feature_v1/pipeline.py
mlops_pipeline_feature_v1/transform.py
mlops_pipeline_feature_v1/utils.py
tests/__init__.py
tests/test_dummy.py
venv_pipeline_feature/bin/rst2html.py
venv_pipeline_feature/bin/rst2html4.py
venv_pipeline_feature/bin/rst2html5.py
venv_pipeline_feature/bin/rst2latex.py
venv_pipeline_feature/bin/rst2man.py
venv_pipeline_feature/bin/rst2odt.py
venv_pipeline_feature/bin/rst2odt_prepstyles.py
venv_pipeline_feature/bin/rst2pseudoxml.py
venv_pipeline_feature/bin/rst2s5.py
venv_pipeline_feature/bin/rst2xetex.py
venv_pipeline_feature/bin/rst2xml.py
venv_pipeline_feature/bin/rstpep2html.py
pipeline_feature-0.0.53.dist-info/LICENSE
pipeline_feature-0.0.53.dist-info/METADATA
pipeline_feature-0.0.53.dist-info/WHEEL
pipeline_feature-0.0.53.dist-info/top_level.txt
pipeline_feature-0.0.53.dist-info/RECORD
